skntk/__init__.py
skntk/kernel.py
scikit_ntk-1.2.1.dist-info/LICENSE
scikit_ntk-1.2.1.dist-info/WHEEL
scikit_ntk-1.2.1.dist-info/METADATA
scikit_ntk-1.2.1.dist-info/RECORD
