Metadata-Version: 2.1
Name: scikit-ntk
Version: 1.2.1
Summary: Implementation of the neural tangent kernel for scikit-learn's Gaussian process module.
Home-page: https://github.com/392781/scikit-ntk
License: BSD-3-Clause
Keywords: sckit-learn,sklearn
Author: Ronaldas P Lencevičius
Author-email: contact@ronaldas.dev
Requires-Python: >=3.8,<3.14
Classifier: Intended Audience :: Science/Research
Classifier: License :: OSI Approved :: BSD License
Classifier: Programming Language :: Python :: 3
Classifier: Programming Language :: Python :: 3.8
Classifier: Programming Language :: Python :: 3.9
Classifier: Programming Language :: Python :: 3.10
Classifier: Programming Language :: Python :: 3.11
Classifier: Programming Language :: Python :: 3
Classifier: Programming Language :: Python :: 3.10
Classifier: Programming Language :: Python :: 3.11
Classifier: Programming Language :: Python :: 3.12
Classifier: Programming Language :: Python :: 3.13
Classifier: Programming Language :: Python :: 3.8
Classifier: Programming Language :: Python :: 3.9
Classifier: Topic :: Scientific/Engineering :: Artificial Intelligence
Classifier: Topic :: Scientific/Engineering :: Mathematics
Classifier: Topic :: Software Development :: Libraries :: Python Modules
Requires-Dist: scikit-learn (>=1.0.0,<2.0.0); python_version >= "3.8" and python_version < "3.10"
Requires-Dist: scikit-learn (>=1.1.3,<2.0.0); python_version >= "3.10"
Project-URL: Bug Tracker, https://github.com/392781/scikit-ntk/issues
Project-URL: Repository, https://github.com/392781/scikit-ntk
